synpp/__init__.py
synpp/__main__.py
synpp/general.py
synpp/parallel.py
synpp/pipeline.py
synpp/progress.py
synpp-1.6.1.dist-info/licenses/LICENSE
synpp-1.6.1.dist-info/METADATA
synpp-1.6.1.dist-info/WHEEL
synpp-1.6.1.dist-info/top_level.txt
synpp-1.6.1.dist-info/RECORD
