Metadata-Version: 2.4
Name: synpp
Version: 1.6.1
Summary: Synthetic population pipeline package for eqasim
Home-page: https://github.com/eqasim-org/synpp
Author: Sebastian Hörl
Author-email: hoerl.sebastian@gmail.com
Keywords: pipeline automation synthetic population dependency management transport
Classifier: Development Status :: 4 - Beta
Classifier: Environment :: Console
Classifier: Intended Audience :: Developers
Classifier: Intended Audience :: Science/Research
Classifier: License :: OSI Approved :: MIT License
Classifier: Programming Language :: Python :: 3
Classifier: Topic :: Scientific/Engineering
Requires-Python: >=3.0
License-File: LICENSE
Requires-Dist: networkx>=3.4
Requires-Dist: PyYAML>=5.1.2
Requires-Dist: pyzmq>=18.1.0
Provides-Extra: test
Requires-Dist: pytest>=5.3.1; extra == "test"
Provides-Extra: example
Requires-Dist: pandas>=0.25.3; extra == "example"
Dynamic: author
Dynamic: author-email
Dynamic: classifier
Dynamic: description
Dynamic: description-content-type
Dynamic: home-page
Dynamic: keywords
Dynamic: license-file
Dynamic: provides-extra
Dynamic: requires-dist
Dynamic: requires-python
Dynamic: summary
